<?xml version="1.0" encoding="UTF-8" standalone="yes"?>

<item>
<title>[COLOR skyblue]   > SUPER[/COLOR][COLOR yellow] MARIO[/COLOR][COLOR red] BROS[/COLOR]</title>
<thumbnail>http://i.imgur.com/cDb3DTV.png</thumbnail>
<fanart>http://i.imgur.com/XDgjUks.jpg</fanart>
<link>http://ignoreme</link>
<externallink>https://raw.githubusercontent.com/RetroBlogPi/MagicPi/master/test2.xml</externallink>
</item>

<item>
<title>[COLOR orange]   > DRAGON BALL ( SUPER / Z / GT / PELICULAS )[/COLOR]</title>
<thumbnail>https://i.imgur.com/GnpHWBq.png</thumbnail>
<fanart>https://i.imgur.com/LwWyPXN.jpg</fanart>
<link>http://ignoreme</link>
<externallink>https://raw.githubusercontent.com/RetroBlogPi/MagicPi/master/dragonball.xml</externallink>
</item>

<item>
<title>[COLOR indianred]   > JUEGO DE TRONOS[/COLOR]</title>
<thumbnail>http://icon-icons.com/icons2/60/PNG/256/gameofthrones6_folder_12129.png</thumbnail>
<fanart>https://wallpaperscraft.com/image/game_of_thrones_series_throne_power_sword_2017_1920x1080.jpg</fanart>
<link>http://ignoreme</link>
<externallink>https://pastebin.com/raw/pZvBmpJc</externallink>
</item>

<item>
<title>[COLOR yellowgreen]   > LA QUE SE AVECINA [/COLOR]</title>
<thumbnail>https://pbs.twimg.com/profile_images/378800000392758484/cf227a971e3e0923ce10e493bedc43a6.jpeg</thumbnail>
<fanart>http://www.bolsamania.com/seriesadictos/wp-content/uploads/2015/04/CCzgAGOWAAMvwjt.jpg-large.jpeg</fanart>
<link>http://ignoreme</link>
<externallink>https://raw.githubusercontent.com/RetroBlogPi/MagicPi/master/LQSA.xml</externallink>
</item>

<item>
<title>[COLOR yellow]   > NARCOS  [/COLOR]</title>
<thumbnail>http://ayayay.tv/wp-content/uploads/2015/10/narcos.jpg</thumbnail>
<fanart>https://okdiario.com/series/img/2016/09/07/narcos-12.jpg</fanart>
<link>http://ignoreme</link>
<externallink>https://pastebin.com/raw/WcppVhfD</externallink>
</item>

<item>
<title>[COLOR skyblue]   > THE LAST KINGDOM      [/COLOR]</title>
<link>ignorame</link>
 <externallink>https://pastebin.com/raw/ddkLwHPa</externallink>
<thumbnail>http://cdn-static.sidereel.com/tv_shows/58198/giant_2x/last_kingdom.jpg</thumbnail>
<fanart></fanart>
</item>

<item>
<title>[COLOR orange]   > TRECE RAZONES[/COLOR]</title>
<link>ignorame</link>
<externallink>https://pastebin.com/raw/Ppxtkqn1</externallink>
<thumbnail>http://www.abc.es/media/play/2017/01/25/13ReasonsWhy_SPA-0191-k0hG-U202323256675GAG-510x700@abc.jpg</thumbnail>
<fanart></fanart>
</item>

<item>
<title>[COLOR indianred]   > ELEMENTARY[/COLOR]</title>
<link>ignorame</link>
<externallink>https://pastebin.com/raw/CzggzL1q</externallink>
<thumbnail>http://es.web.img1.acsta.net/pictures/14/03/18/09/36/485305.jpg</thumbnail>
<fanart></fanart>
</item>

<item>
<title>[COLOR yellowgreen]   > VIKINGS[/COLOR]</title>
<link>http://ignoreme</link>
<externallink>https://pastebin.com/raw/GNi3A6qY</externallink>
<thumbnail>http://solopormega.com/wp-content/uploads/2015/07/vikings.jpg</thumbnail>
<fanart></fanart>
</item>

<item>
<title>[COLOR yellow]   > FEAR THE WALKING DEAD  [/COLOR]</title>
<thumbnail>http://my-film.in/wp-content/uploads/2016/04/fear-the-walking-dead-second-season.jpg</thumbnail>
<fanart></fanart>
<link>http://ignoreme</link>
<externallink>https://pastebin.com/raw/dsaeDhRZ</externallink>
</item>

<item>
<title>[COLOR skyblue]   > IRON FIRST     [/COLOR]</title>
<link>ignorame</link>
 <externallink>https://pastebin.com/raw/Cg1AWvEL</externallink>
<thumbnail>http://solopormega.com/wp-content/uploads/2017/03/iron-fist.jpg</thumbnail>
<fanart></fanart>
</item>











